__init__.py
botik_telebot/__init__.py
botik_telebot/app.py
botik_telebot/api/__init__.py
botik_telebot/api/api.py
botik_telebot/api/api_type.py
botik_telebot/api/send_message.py
botik_telebot/api/attachment_handlers/__init__.py
botik_telebot/api/attachment_handlers/photo_attachment_handler.py
botik_telebot/input/__init__.py
botik_telebot/input/keyboard/__init__.py
botik_telebot/input/keyboard/keyboard_markup.py
botik_telebot/input/keyboard/markup_factory.py
botik_telebot/input/keyboard/button/__init__.py
botik_telebot/input/keyboard/button/button.py
botik_telebot/input/keyboard/button/button_factory.py
botik_telebot/input/message_handlers/__init__.py
botik_telebot/input/message_handlers/raw_message_handlers.py
botik_telebot/page/__init__.py
botik_telebot/page/page_factory.py
botik_telebot-0.0.2.dist-info/LICENSE
botik_telebot-0.0.2.dist-info/METADATA
botik_telebot-0.0.2.dist-info/WHEEL
botik_telebot-0.0.2.dist-info/top_level.txt
botik_telebot-0.0.2.dist-info/RECORD
